bstruct/__init__.py
bstruct-0.6.1.dist-info/LICENSE
bstruct-0.6.1.dist-info/METADATA
bstruct-0.6.1.dist-info/WHEEL
bstruct-0.6.1.dist-info/RECORD
