Metadata-Version: 2.1
Name: bstruct
Version: 0.6.1
Summary: Simple and efficient binary (de)serialization using type annotations.
Home-page: https://github.com/flxbe/bstruct
License: MIT
Author: flxbe
Author-email: flxbe@mailbox.org
Requires-Python: >=3.9,<4.0
Classifier: Intended Audience :: Developers
Classifier: License :: OSI Approved :: MIT License
Classifier: Programming Language :: Python :: 3
Classifier: Programming Language :: Python :: 3.9
Classifier: Programming Language :: Python :: 3.10
Classifier: Programming Language :: Python :: 3.11
Classifier: Programming Language :: Python :: 3.12
Classifier: Programming Language :: Python :: Implementation :: CPython
Classifier: Topic :: Software Development :: Libraries :: Python Modules
Classifier: Typing :: Typed
Project-URL: Changelog, https://github.com/flxbe/bstruct/blob/main/CHANGELOG.md
Project-URL: Documentation, https://bstruct.readthedocs.io
Project-URL: Repository, https://github.com/flxbe/bstruct
